MANIFEST.in
README.md
setup.py
streamlit_jina/__init__.py
streamlit_jina.egg-info/PKG-INFO
streamlit_jina.egg-info/SOURCES.txt
streamlit_jina.egg-info/dependency_links.txt
streamlit_jina.egg-info/requires.txt
streamlit_jina.egg-info/top_level.txt